{
  "db_name": "PostgreSQL",
  "query": "\n            SELECT COALESCE(SUM(amount), 0) as \"total!\"\n            FROM payments\n            WHERE status = $1\n              AND paid_at::date = $2\n            ",
  "describe": {
    "columns": [
      {
        "ordinal": 0,
        "name": "total!",
        "type_info": "Numeric"
      }
    ],
    "parameters": {
      "Left": [
        "Text",
        "Date"
      ]
    },
    "nullable": [
      null
    ]
  },
  "hash": "674cc9de80909e3131b4b21ab3e05a961dabda645f878f628277c4a3239c132f"
}
